[
	{
		"name": "Metodologia RUT",
		"label": "kind/rut",
		"variables": [
			{
				"title":"Relevância",
				"name":"relevancia",
				"calc":"mul",
				"values":[
					{"name": "XS", "score": 1, "questions": [
						"Não faz parte do conceito do produto. Seria bom ter, mas ficamos bem sem ele"
					]},
					{"name": "S", "score": 2, "questions": [
						"É relacionado ao conceito do produto, seria bom ter"
					]},
					{"name": "M", "score": 3, "questions": [
						"Importante para o conceito do produto"
					]},
					{"name": "L", "score": 4, "questions": [
						"Muito importante, o produto fica desfalcado sem isso"
					]},
					{"name": "XL", "score": 5, "questions": [
						"Não há produto sem este item"
					]}
				]
			},
			{
				"title":"Urgência",
				"name":"urgencia",
				"calc":"mul",
				"values":[
					{"name": "XS", "score": 1, "questions": [
						"Implementar agora não faz diferença. Dá para esperar"
					]},
					{"name": "S", "score": 2, "questions": [
						"Não é bom ficar sem, mas dá para esperar"
					]},
					{"name": "M", "score": 3, "questions": [
						"É desejável lançar em breve, na próxima release talvez"
					]},
					{"name": "L", "score": 4, "questions": [
						"Teremos problemas se não tiver na próxima release"
					]},
					{"name": "XL", "score": 5, "questions": [
						"É imediato, não podemos esperar a próxima release"
					]}
				]
			},
			{
				"title":"Tendência",
				"name":"tendencia",
				"calc":"mul",
				"values":[
					{"name": "XS", "score": 1, "questions": [
						"A primeira impressão não é boa, mas o usuário se acostuma"
					]},
					{"name": "S", "score": 2, "questions": [
						"Pode ser problemático para o usuário continuar sem isso"
					]},
					{"name": "M", "score": 3, "questions": [
						"É certo que o usuário será prejudicado sem isso"
					]},
					{"name": "L", "score": 4, "questions": [
						"O prejuízo para o usuário não é só certo como aumenta com o tempo"
					]},
					{"name": "XL", "score": 5, "questions": [
						"Piora muito a cada dia, é extremamente desgastante para o usuário"
					]}
				]
			}
		],
		"methodology":"https://code.likeagirl.io/priorizando-sem-trauma-como-ordenar-seu-backlog-de-produto-d143b6037c8d"
	}
]